{
    "2845.TW": {
        "名稱": "遠東銀",
        "加入日期": "2026-04-01",
        "加入價格": 12.55
    },
    "2484.TW": {
        "名稱": "希華",
        "加入日期": "2026-03-24",
        "加入價格": 29.4
    },
    "2231.TW": {
        "名稱": "為升",
        "加入日期": "2026-03-24",
        "加入價格": 99.4
    },
    "2049.TW": {
        "名稱": "上銀",
        "加入日期": "2026-04-09",
        "加入價格": 245.0
    },
    "4956.TW": {
        "名稱": "光鋐",
        "加入日期": "2026-04-13",
        "加入價格": 38.0
    },
    "6789.TW": {
        "名稱": "采鈺",
        "加入日期": "2026-04-13",
        "加入價格": 370.0
    },
    "6949.TW": {
        "名稱": "沛爾生醫-創",
        "加入日期": "2026-04-08",
        "加入價格": 608.0
    },
        "2303.TW": {
        "名稱": "聯電",
        "加入日期": "2026-04-08",
        "加入價格": 60.3
    },
    "3055.TW": {
        "名稱": "蔚華科",
        "加入日期": "2026-04-08",
        "加入價格": 60.0
    },
    "5244.TW": {
        "名稱": "弘凱",
        "加入日期": "2026-03-19",
        "加入價格": 38.35
    }
}